erf_gui/__about__.py
erf_gui/__init__.py
erf_gui/__main__.py
erf_gui/core.py
erf_gui/cli/__init__.py
erf_gui-0.0.2.dist-info/METADATA
erf_gui-0.0.2.dist-info/WHEEL
erf_gui-0.0.2.dist-info/entry_points.txt
erf_gui-0.0.2.dist-info/licenses/LICENSE.txt
erf_gui-0.0.2.dist-info/RECORD
